usbclassifier/__init__.py
usbclassifier/classifier.py
usbclassifier-0.1.3.dist-info/METADATA
usbclassifier-0.1.3.dist-info/RECORD
usbclassifier-0.1.3.dist-info/WHEEL
usbclassifier-0.1.3.dist-info/top_level.txt
