Metadata-Version: 2.1
Name: usbclassifier
Version: 0.1.3
Summary: Bagging Classifier with Under Sampling
Home-page: https://github.com/nekoumei/usbclassifier
Author: nekoumei
Author-email: nekoumei@gmail.com
License: MIT
Platform: UNKNOWN
Classifier: Programming Language :: Python :: 3.6
Classifier: License :: OSI Approved :: MIT License
Classifier: Development Status :: 4 - Beta
Classifier: Environment :: MacOS X
Classifier: Topic :: Scientific/Engineering :: Artificial Intelligence
Requires-Dist: pandas
